fossil_delta.so
fossil_delta-17.12.0.dist-info/METADATA
fossil_delta-17.12.0.dist-info/metadata.json
fossil_delta-17.12.0.dist-info/top_level.txt
fossil_delta-17.12.0.dist-info/WHEEL
fossil_delta-17.12.0.dist-info/RECORD
fossil_delta-17.12.0.dist-info/DESCRIPTION.rst
