Metadata-Version: 2.0
Name: fossil-delta
Version: 17.12.0
Summary: thin wrapper of string delta functions from fossil SCM
Home-page: https://github.com/kurtbrose/fossil-delta
Author: UNKNOWN
Author-email: UNKNOWN
License: UNKNOWN
Platform: any
